pka_predictor/__init__.py
pka_predictor/__main__.py
pka_predictor/predict.py
pka_predictor/GNN/GNN.py
pka_predictor/GNN/__init__.py
pka_predictor/GNN/argParser.py
pka_predictor/GNN/change_ionization.py
pka_predictor/GNN/extract.py
pka_predictor/GNN/featurizer.py
pka_predictor/GNN/hyper_tune.py
pka_predictor/GNN/hyperoptimize.py
pka_predictor/GNN/main.py
pka_predictor/GNN/plot_and_print.py
pka_predictor/GNN/predict.py
pka_predictor/GNN/prepare_set.py
pka_predictor/GNN/split_train_test_by_TC.py
pka_predictor/GNN/train.py
pka_predictor/GNN/train_pKa_predictor.py
pka_predictor/GNN/transfer_chirality.py
pka_predictor/GNN/usage.py
pka_predictor/GNN/utils.py
pka_predictor/Model/model_4-4.pth
pka_predictor_moitessier-0.1.12.dist-info/licenses/LICENSE
pka_predictor_moitessier-0.1.12.dist-info/METADATA
pka_predictor_moitessier-0.1.12.dist-info/WHEEL
pka_predictor_moitessier-0.1.12.dist-info/entry_points.txt
pka_predictor_moitessier-0.1.12.dist-info/top_level.txt
pka_predictor_moitessier-0.1.12.dist-info/RECORD
