Metadata-Version: 2.4
Name: pka_predictor_moitessier
Version: 0.1.12
Summary: Graph-based pKa prediction for small molecules
Home-page: https://github.com/MoitessierLab/pKa-predictor
Author: Moitessier Lab
Author-email: nicolas.moitessier@mcgill.ca
License: GPL-3.0
Keywords: pKa prediction GNN chemistry rdkit
Classifier: Programming Language :: Python :: 3
Classifier: License :: OSI Approved :: GNU General Public License v3 (GPLv3)
Classifier: Operating System :: OS Independent
Requires-Python: >=3.8
License-File: LICENSE
Requires-Dist: torch
Requires-Dist: torch_geometric
Requires-Dist: pandas
Requires-Dist: numpy
Requires-Dist: rdkit
Requires-Dist: seaborn
Requires-Dist: hyperopt
Requires-Dist: scikit-learn
Dynamic: author
Dynamic: author-email
Dynamic: classifier
Dynamic: description
Dynamic: description-content-type
Dynamic: home-page
Dynamic: keywords
Dynamic: license
Dynamic: license-file
Dynamic: requires-dist
Dynamic: requires-python
Dynamic: summary
